LICENSE
README.markdown
requirements.txt
setup.cfg
setup.py
sriovmng
test-requirements.txt
tox.ini
sriovlib/__init__.py
sriovlib/exceptions.py
sriovlib/sriov.py
sriovlib/utils.py
sriovmng.egg-info/PKG-INFO
sriovmng.egg-info/SOURCES.txt
sriovmng.egg-info/dependency_links.txt
sriovmng.egg-info/not-zip-safe
sriovmng.egg-info/pbr.json
sriovmng.egg-info/requires.txt
sriovmng.egg-info/top_level.txt