Metadata-Version: 1.1
Name: sriovmng
Version: 0.1.0
Summary: UNKNOWN
Home-page: https://github.com/novel/sriovmng
Author: Roman Bogorodskiy
Author-email: novel@FreeBSD.org
License: Apache-2
Platform: UNKNOWN
Classifier: Development Status :: 4 - Beta
Classifier: Environment :: Console
Classifier: Intended Audience :: System Administrators
Classifier: Intended Audience :: Information Technology
Classifier: License :: OSI Approved :: Apache Software License
Classifier: Operating System :: POSIX :: Linux
Classifier: Programming Language :: Python
